video2psp/__init__.py
video2psp/psp.py
video2psp-0.3.1.dist-info/METADATA
video2psp-0.3.1.dist-info/WHEEL
video2psp-0.3.1.dist-info/entry_points.txt
video2psp-0.3.1.dist-info/top_level.txt
video2psp-0.3.1.dist-info/RECORD
