Metadata-Version: 2.2
Name: video2psp
Version: 0.3.1
Summary: A CLI tool to convert video to PSP MP4 with user-selected audio and subtitle tracks.
Home-page: https://github.com/ghurone/video2psp
Author: Erick Ghuron
Author-email: ghuron@usp.br
Requires-Python: >=3.11
Dynamic: author
Dynamic: author-email
Dynamic: home-page
Dynamic: requires-python
Dynamic: summary
